unitradeapi/__init__.py
unitradeapi/binance.py
unitradeapi/bybit.py
unitradeapi-0.124.dist-info/LICENSE.md
unitradeapi-0.124.dist-info/METADATA
unitradeapi-0.124.dist-info/WHEEL
unitradeapi-0.124.dist-info/top_level.txt
unitradeapi-0.124.dist-info/RECORD
